datamode/__init__.py
datamode/entry.py
datamode/errors.py
datamode/interface.py
datamode/settings.py
datamode/dist/index.js
datamode/jupyter-config/nbconfig/notebook.d/datamode.json
datamode/react/__init__.py
datamode/react/arrow.py
datamode/react/chart.py
datamode/react/datamode_app.py
datamode/react/kde.py
datamode/react/reactbridge.py
datamode/react/reactdata.py
datamode/react/stats.py
datamode/react/altaircharts/__init__.py
datamode/react/altaircharts/altair_build.py
datamode/react/altaircharts/altair_utils.py
datamode/transforms/__init__.py
datamode/transforms/columnartransform.py
datamode/transforms/data_context.py
datamode/transforms/db_transforms.py
datamode/transforms/load.py
datamode/transforms/nlp.py
datamode/transforms/transforms.py
datamode/transforms/twocoltransform.py
datamode/transforms/core/__init__.py
datamode/transforms/core/context.py
datamode/transforms/core/dataset.py
datamode/transforms/core/transform_core.py
datamode/transforms/core/transform_result.py
datamode/transforms/core/transform_state.py
datamode/transforms/expressions/__init__.py
datamode/transforms/expressions/execution_manager.py
datamode/transforms/expressions/expression_node.py
datamode/transforms/expressions/expression_transform.py
datamode/transforms/expressions/linear_execution.py
datamode/transforms/expressions/ops.py
datamode/transforms/expressions/parser.py
datamode/transforms/expressions/set_functions.py
datamode/transforms/expressions/tablecolumn.py
datamode/transforms/expressions/virtualtable.py
datamode/utils/__init__.py
datamode/utils/cfgutils.py
datamode/utils/colorizer.py
datamode/utils/data.py
datamode/utils/dbutils.py
datamode/utils/exceptionutils.py
datamode/utils/logutils.py
datamode/utils/notebook.py
datamode/utils/perf.py
datamode/utils/singleton.py
datamode/utils/timer.py
datamode/utils/usageutils.py
datamode/utils/utils.py
datamode/utils/validator.py
datamode/utils/wordvecs.py
datamode-0.0.10.dist-info/METADATA
datamode-0.0.10.dist-info/RECORD
datamode-0.0.10.dist-info/WHEEL
datamode-0.0.10.dist-info/top_level.txt
