Metadata-Version: 2.1
Name: datamode
Version: 0.0.10
Summary: A tool to quickly build data science pipelines
Home-page: https://www.datamode.com
Author: Vaughn Koch
Author-email: code@datamode.com
License: Apache 2.0
Project-URL: Main website, https://www.datamode.com
Project-URL: Documentation, https://datamode.readthedocs.io/
Project-URL: Source, https://github.com/datamode/datamode/
Project-URL: Tracker, https://github.com/datamode/datamode/issues
Keywords: datamode,dataviz,data science,data transformation,feature engineering,data prep,data preparation,data munging,data visualization
Platform: UNKNOWN
Classifier: Development Status :: 4 - Beta
Classifier: Programming Language :: Python
Classifier: Programming Language :: Python :: 3 :: Only
Classifier: Programming Language :: Python :: 3.6
Classifier: Programming Language :: Python :: 3.7
Classifier: Topic :: Utilities
Classifier: Topic :: Software Development :: User Interfaces
Classifier: Topic :: Scientific/Engineering :: Visualization
Classifier: Topic :: Scientific/Engineering :: Artificial Intelligence
Classifier: Operating System :: OS Independent
Classifier: License :: OSI Approved :: Apache Software License
Requires-Dist: Pygments (>=2.3.1)
Requires-Dist: colorama (>=0.4.1)
Requires-Dist: pytz (>=2018.9)
Requires-Dist: python-dateutil (>=2.7.5)
Requires-Dist: pyparsing (>=2.3.1)
Requires-Dist: SQLAlchemy (>=1.2.16)
Requires-Dist: mysql-connector-python (>=8.0.14)
Requires-Dist: psycopg2-binary (>=2.7.6.1)
Requires-Dist: boto3 (>=1.9.83)
Requires-Dist: numpy (>=1.16.0)
Requires-Dist: scipy (>=1.2.0)
Requires-Dist: pandas (>=0.23.4)
Requires-Dist: scikit-learn (>=0.20.2)
Requires-Dist: gensim (>=3.6.0)
Requires-Dist: altair (>=2.3.0)
Requires-Dist: statsmodels (>=0.9.0)
Requires-Dist: seaborn (>=0.9.0)
Requires-Dist: jupyter (>=1.0.0)
Requires-Dist: jupyter-contrib-nbextensions (>=0.5.1)
Requires-Dist: pyarrow (>=0.12.0)
Requires-Dist: jupyter-react (>=0.1.3)
Requires-Dist: analytics-python (>=1.2.9)
